pixegami_hello/__init__.py
pixegami_hello/main.py
pixegami_hello-0.3.0.dist-info/METADATA
pixegami_hello-0.3.0.dist-info/WHEEL
pixegami_hello-0.3.0.dist-info/entry_points.txt
pixegami_hello-0.3.0.dist-info/top_level.txt
pixegami_hello-0.3.0.dist-info/RECORD
