Metadata-Version: 2.1
Name: pixegami-hello
Version: 0.3.0
